openwisp_controller/__init__.py
openwisp_controller/admin.py
openwisp_controller/base.py
openwisp_controller/checks.py
openwisp_controller/context_processors.py
openwisp_controller/migrations.py
openwisp_controller/mixins.py
openwisp_controller/routing.py
openwisp_controller/serializers.py
openwisp_controller/settings.py
openwisp_controller/urls.py
openwisp_controller/vpn_backends.py
openwisp_controller/config/__init__.py
openwisp_controller/config/admin.py
openwisp_controller/config/apps.py
openwisp_controller/config/crypto.py
openwisp_controller/config/exceptions.py
openwisp_controller/config/exportable.py
openwisp_controller/config/filters.py
openwisp_controller/config/handlers.py
openwisp_controller/config/models.py
openwisp_controller/config/settings.py
openwisp_controller/config/signals.py
openwisp_controller/config/tasks.py
openwisp_controller/config/tasks_zerotier.py
openwisp_controller/config/urls.py
openwisp_controller/config/utils.py
openwisp_controller/config/validators.py
openwisp_controller/config/views.py
openwisp_controller/config/widgets.py
openwisp_controller/config/api/__init__.py
openwisp_controller/config/api/download_views.py
openwisp_controller/config/api/filters.py
openwisp_controller/config/api/serializers.py
openwisp_controller/config/api/urls.py
openwisp_controller/config/api/views.py
openwisp_controller/config/api/zerotier_service.py
openwisp_controller/config/base/__init__.py
openwisp_controller/config/base/base.py
openwisp_controller/config/base/channels_consumer.py
openwisp_controller/config/base/config.py
openwisp_controller/config/base/device.py
openwisp_controller/config/base/device_group.py
openwisp_controller/config/base/multitenancy.py
openwisp_controller/config/base/tag.py
openwisp_controller/config/base/template.py
openwisp_controller/config/base/vpn.py
openwisp_controller/config/controller/__init__.py
openwisp_controller/config/controller/urls.py
openwisp_controller/config/controller/views.py
openwisp_controller-1.2.dist-info/licenses/LICENSE
openwisp_controller-1.2.dist-info/METADATA
openwisp_controller-1.2.dist-info/WHEEL
openwisp_controller-1.2.dist-info/top_level.txt
openwisp_controller-1.2.dist-info/RECORD
