Metadata-Version: 2.4
Name: openwisp-controller
Version: 1.2
Summary: OpenWISP Controller
Home-page: http://openwisp.org
Download-URL: https://github.com/openwisp/openwisp-controller/releases
Author: OpenWISP
Author-email: support@openwisp.io
License: GPL3
Keywords: django,netjson,openwrt,networking,openwisp
Platform: Platform Independent
Classifier: Development Status :: 5 - Production/Stable
Classifier: Environment :: Web Environment
Classifier: Topic :: Internet :: WWW/HTTP
Classifier: Topic :: System :: Networking
Classifier: Intended Audience :: Developers
Classifier: License :: OSI Approved :: GNU General Public License v3 (GPLv3)
Classifier: Operating System :: OS Independent
Classifier: Framework :: Django
Classifier: Programming Language :: Python :: 3
License-File: LICENSE
Requires-Dist: django-sortedm2m~=4.0.0
Requires-Dist: django-reversion~=6.0.0
Requires-Dist: django-taggit~=6.1.0
Requires-Dist: netjsonconfig~=1.2.0
Requires-Dist: django-x509~=1.3.0
Requires-Dist: django-loci~=1.2.0
Requires-Dist: django-flat-json-widget~=0.4.0
Requires-Dist: openwisp-users~=1.2.0
Requires-Dist: openwisp-utils[celery,channels]~=1.2.0
Requires-Dist: openwisp-notifications~=1.2.0
Requires-Dist: openwisp-ipam~=1.2.0
Requires-Dist: djangorestframework-gis~=1.2.0
Requires-Dist: paramiko~=4.0.0
Requires-Dist: scp~=0.15.0
Requires-Dist: django-cache-memoize~=0.2.1
Requires-Dist: shortuuid~=1.0.13
Requires-Dist: netaddr~=1.3.0
Requires-Dist: django-import-export~=4.3.10
Dynamic: author
Dynamic: author-email
Dynamic: classifier
Dynamic: description
Dynamic: download-url
Dynamic: home-page
Dynamic: keywords
Dynamic: license
Dynamic: license-file
Dynamic: platform
Dynamic: requires-dist
Dynamic: summary
